[{"customer_id":111,"email":"mianinotti32@clickbank.net","donations":[{"payment_id":53,"amount":155.47,"payment_date":"2020-08-19","payment_method":"PayPal","status":"failed"},{"payment_id":180,"amount":6.55,"payment_date":"2022-05-11","payment_method":"credit card","status":"pending"},{"payment_id":877,"amount":193.8,"payment_date":"2020-10-10","payment_method":"credit card","status":"completed"}],"customer_profile":{"region":"Midlands","shirt_size":"None","donates_to_charity":"Never","bikes_to_work":"Once"}},{"customer_id":112,"email":"bcubley33@cnn.com","donations":[{"payment_id":851,"amount":159.38,"payment_date":"2020-07-10","payment_method":"credit card","status":"completed"},{"payment_id":972,"amount":94.22,"payment_date":"2020-04-16","payment_method":"credit card","status":"failed"}],"customer_profile":{"region":"East of England","shirt_size":"S","donates_to_charity":"Weekly","bikes_to_work":"Weekly"}},{"customer_id":113,"email":"ktuhy34@ezinearticles.com","donations":[{"payment_id":54,"amount":129.17,"payment_date":"2022-05-02","payment_method":"credit card","status":"pending"},{"payment_id":512,"amount":6.12,"payment_date":"2022-11-02","payment_method":"PayPal","status":"completed"},{"payment_id":598,"amount":54.52,"payment_date":"2021-03-11","payment_method":"debit card","status":"pending"},{"payment_id":929,"amount":116.95,"payment_date":"2020-01-22","payment_method":"PayPal","status":"pending"},{"payment_id":986,"amount":193.07,"payment_date":"2021-09-30","payment_method":"PayPal","status":"completed"},{"payment_id":994,"amount":135.72,"payment_date":"2021-10-13","payment_method":"debit card","status":"pending"}],"customer_profile":{"region":"London and South East","shirt_size":"XS","donates_to_charity":"Never","bikes_to_work":"Never"}},{"customer_id":114,"email":"spryer35@topsy.com","donations":[{"payment_id":71,"amount":48.92,"payment_date":"2020-10-03","payment_method":"PayPal","status":"completed"},{"payment_id":201,"amount":16.04,"payment_date":"2021-01-01","payment_method":"debit card","status":"failed"},{"payment_id":260,"amount":117.86,"payment_date":"2021-07-19","payment_method":"PayPal","status":"completed"},{"payment_id":411,"amount":29.35,"payment_date":"2022-05-02","payment_method":"credit card","status":"failed"},{"payment_id":544,"amount":192.99,"payment_date":"2020-05-14","payment_method":"credit card","status":"failed"}],"customer_profile":{"region":"London and South East","shirt_size":"2XL","donates_to_charity":"Weekly","bikes_to_work":"Yearly"}},{"customer_id":115,"email":"ksurgood36@php.net","donations":[{"payment_id":325,"amount":71.16,"payment_date":"2022-01-28","payment_method":"PayPal","status":"failed"},{"payment_id":375,"amount":50.35,"payment_date":"2020-12-17","payment_method":"PayPal","status":"pending"},{"payment_id":530,"amount":151.54,"payment_date":"2021-01-29","payment_method":"credit card","status":"completed"},{"payment_id":559,"amount":69.63,"payment_date":"2022-11-10","payment_method":"debit card","status":"completed"}],"customer_profile":{"region":"London and South East","shirt_size":"None","donates_to_charity":"Yearly","bikes_to_work":"Monthly"}}]